nbmask/__init__.py
nbmask-0.0.5.dist-info/WHEEL
nbmask-0.0.5.dist-info/METADATA
nbmask-0.0.5.dist-info/RECORD
