Metadata-Version: 2.3
Name: nbmask
Version: 0.0.5
Summary: IPython extension to mask sensitive data
Keywords: ipython,notebook,extension,privacy
Author: furechan
Author-email: furechan <furechan@xsmail.com>
Classifier: Development Status :: 2 - Pre-Alpha
Classifier: Programming Language :: Python :: 3
Classifier: License :: OSI Approved :: MIT License
Requires-Python: >=3.10
Project-URL: homepage, https://github.com/furechan/nbmask
